{"_context" : {
    "_types" : {
      "DocumentMetaData" : {
        "_feature_types" : {"sofa" : "_ref" } }, 
      "FeatureDefinition" : {
        "_feature_types" : {"layer" : "_ref" } }, 
      "LayerDefinition" : { }, 
      "NamedEntity" : {
        "_feature_types" : {"sofa" : "_ref" } }, 
      "Relation" : {
        "_feature_types" : {"sofa" : "_ref",  "Dependent" : "_ref",  "Governor" : "_ref" } }, 
      "Sentence" : {
        "_feature_types" : {"sofa" : "_ref" } }, 
      "Sofa" : {
        "_feature_types" : {"sofaArray" : "_ref" } }, 
      "TagsetDescription" : {
        "_feature_types" : {"sofa" : "_ref",  "tags" : "_ref" } }, 
      "Token" : {
        "_feature_types" : {"sofa" : "_ref",  "parent" : "_ref",  "lemma" : "_ref",  "stem" : "_ref",  "pos" : "_ref",  "morph" : "_ref",  "form" : "_ref" } }, 
      "DocumentAnnotation" : {
        "_feature_types" : {"sofa" : "_ref" }, 
        "_subtypes" : ["DocumentMetaData" ] }, 
      "Annotation" : {
        "_feature_types" : {"sofa" : "_ref" }, 
        "_subtypes" : ["DocumentAnnotation",  "NamedEntity",  "Relation",  "Sentence",  "TagsetDescription",  "Token" ] }, 
      "AnnotationBase" : {
        "_feature_types" : {"sofa" : "_ref" }, 
        "_subtypes" : ["Annotation" ] }, 
      "TOP" : {
        "_subtypes" : ["AnnotationBase",  "FeatureDefinition",  "LayerDefinition",  "Sofa" ] } } }, 
  "_views" : {
    "_InitialView" : {
      "FeatureDefinition" : [
        {"layer" : 8258,  "name" : "referenceRelation",  "uiName" : "referenceRelation" }, 
        {"layer" : 8258,  "name" : "referenceType",  "uiName" : "referenceType" }, 
        {"layer" : 8269,  "name" : "value",  "uiName" : "Features" }, 
        {"layer" : 8276,  "name" : "PosValue",  "uiName" : "XPOS" }, 
        {"layer" : 8276,  "name" : "coarseValue",  "uiName" : "UPOS" }, 
        {"layer" : 8287,  "name" : "identifier",  "uiName" : "identifier" }, 
        {"layer" : 8287,  "name" : "value",  "uiName" : "value" }, 
        {"layer" : 8298,  "name" : "value",  "uiName" : "Lemma" }, 
        {"layer" : 8305,  "name" : "value",  "uiName" : "Form" }, 
        {"layer" : 8312,  "name" : "arguments",  "uiName" : "arguments" }, 
        {"layer" : 8312,  "name" : "category",  "uiName" : "category" }, 
        {"layer" : 8323,  "name" : "chunkValue",  "uiName" : "Tag" }, 
        {"layer" : 8330,  "name" : "DependencyType",  "uiName" : "Relation" }, 
        {"layer" : 8330,  "name" : "flavor",  "uiName" : "Flavor" }, 
        {"layer" : 8341,  "name" : "operation",  "uiName" : "Operation" }, 
        {"layer" : 8341,  "name" : "value",  "uiName" : "Correction" }, 
        {"layer" : 8352,  "name" : "RelationType",  "uiName" : "RelationType" } ], 
      "LayerDefinition" : [8258,  8269,  8276,  8287,  8298,  8305,  8312,  8323,  8330,  8341,  8352 ], 
      "DocumentMetaData" : [
        {"sofa" : 1,  "end" : 2190,  "language" : "x-unspecified",  "documentTitle" : "Article_370.txt",  "documentId" : "admin",  "documentUri" : "file:/C:/Users/Vandana/.inception/repository/project/9/document/683/source/admin",  "collectionId" : "file:/C:/Users/Vandana/.inception/repository/project/9/document/683/source/",  "documentBaseUri" : "file:/C:/Users/Vandana/.inception/repository/project/9/document/683/source/",  "isLastSegment" : false } ], 
      "TagsetDescription" : [
        {"sofa" : 1,  "layer" : "de.tudarmstadt.ukp.dkpro.core.api.syntax.type.dependency.Dependency",  "name" : "UD Universal Dependencies (v2)",  "input" : false }, 
        {"sofa" : 1,  "layer" : "de.tudarmstadt.ukp.dkpro.core.api.ner.type.NamedEntity",  "name" : "Named Entity Tags",  "input" : false }, 
        {"sofa" : 1,  "layer" : "de.tudarmstadt.ukp.dkpro.core.api.transform.type.SofaChangeAnnotation",  "name" : "Operation",  "input" : false }, 
        {"sofa" : 1,  "layer" : "de.tudarmstadt.ukp.dkpro.core.api.lexmorph.type.pos.POS",  "name" : "UD Universal POS tags (v2)",  "input" : false }, 
        {"sofa" : 1,  "layer" : "webanno.custom.Relation",  "name" : "Relation Labels",  "input" : false } ], 
      "NamedEntity" : [
        {"sofa" : 1,  "end" : 5,  "value" : "SUS.NUMBER" }, 
        {"sofa" : 1,  "begin" : 6,  "end" : 8,  "value" : "LOC.STATE" }, 
        {"sofa" : 1,  "begin" : 9,  "end" : 19,  "value" : "SUS.AFFIL" }, 
        {"sofa" : 1,  "begin" : 33,  "end" : 52,  "value" : "CRIME.CAT" }, 
        {"sofa" : 1,  "begin" : 77,  "end" : 82,  "value" : "SUS.NUMBER" }, 
        {"sofa" : 1,  "begin" : 83,  "end" : 85,  "value" : "LOC.STATE" }, 
        {"sofa" : 1,  "begin" : 86,  "end" : 96,  "value" : "SUS.AFFIL" }, 
        {"sofa" : 1,  "begin" : 120,  "end" : 129,  "value" : "SP.COMMON" }, 
        {"sofa" : 1,  "begin" : 131,  "end" : 137,  "value" : "CRIME.CAT" }, 
        {"sofa" : 1,  "begin" : 298,  "end" : 326,  "value" : "AUTH.SEIZE" }, 
        {"sofa" : 1,  "begin" : 342,  "end" : 347,  "value" : "SUS.NUMBER" }, 
        {"sofa" : 1,  "begin" : 391,  "end" : 412,  "value" : "CRIME.CAT" }, 
        {"sofa" : 1,  "begin" : 413,  "end" : 427,  "value" : "SP.SPECIFIC" }, 
        {"sofa" : 1,  "begin" : 433,  "end" : 451,  "value" : "ROUTE.SRC" }, 
        {"sofa" : 1,  "begin" : 538,  "end" : 543,  "value" : "DATE" }, 
        {"sofa" : 1,  "begin" : 566,  "end" : 571,  "value" : "SUS.NUMBER" }, 
        {"sofa" : 1,  "begin" : 659,  "end" : 677,  "value" : "SUS.AFFIL" }, 
        {"sofa" : 1,  "begin" : 1444,  "end" : 1472,  "value" : "AUTH.SEIZE" },  6989,  7067,  7145,  7223,  7301,  7379, 
        {"sofa" : 1,  "begin" : 1988,  "end" : 2011,  "value" : "OUTCOME" } ], 
      "Sentence" : [
        {"sofa" : 1,  "end" : 477 }, 
        {"sofa" : 1,  "begin" : 478,  "end" : 603 }, 
        {"sofa" : 1,  "begin" : 604,  "end" : 632 }, 
        {"sofa" : 1,  "begin" : 633,  "end" : 764 }, 
        {"sofa" : 1,  "begin" : 765,  "end" : 872 }, 
        {"sofa" : 1,  "begin" : 873,  "end" : 939 }, 
        {"sofa" : 1,  "begin" : 940,  "end" : 1086 }, 
        {"sofa" : 1,  "begin" : 1087,  "end" : 1156 }, 
        {"sofa" : 1,  "begin" : 1157,  "end" : 1340 }, 
        {"sofa" : 1,  "begin" : 1341,  "end" : 1439 }, 
        {"sofa" : 1,  "begin" : 1440,  "end" : 1675 }, 
        {"sofa" : 1,  "begin" : 1676,  "end" : 1720 }, 
        {"sofa" : 1,  "begin" : 1721,  "end" : 1884 }, 
        {"sofa" : 1,  "begin" : 1885,  "end" : 1936 }, 
        {"sofa" : 1,  "begin" : 1937,  "end" : 1984 }, 
        {"sofa" : 1,  "begin" : 1985,  "end" : 2166 }, 
        {"sofa" : 1,  "begin" : 2167,  "end" : 2189 } ], 
      "Token" : [
        {"sofa" : 1,  "end" : 5 }, 
        {"sofa" : 1,  "begin" : 6,  "end" : 8 }, 
        {"sofa" : 1,  "begin" : 9,  "end" : 19 }, 
        {"sofa" : 1,  "begin" : 20,  "end" : 25 }, 
        {"sofa" : 1,  "begin" : 26,  "end" : 32 }, 
        {"sofa" : 1,  "begin" : 33,  "end" : 42 }, 
        {"sofa" : 1,  "begin" : 43,  "end" : 52 }, 
        {"sofa" : 1,  "begin" : 52,  "end" : 53 }, 
        {"sofa" : 1,  "begin" : 54,  "end" : 60 }, 
        {"sofa" : 1,  "begin" : 61,  "end" : 63 }, 
        {"sofa" : 1,  "begin" : 64,  "end" : 70 }, 
        {"sofa" : 1,  "begin" : 71,  "end" : 75 }, 
        {"sofa" : 1,  "begin" : 77,  "end" : 82 }, 
        {"sofa" : 1,  "begin" : 83,  "end" : 85 }, 
        {"sofa" : 1,  "begin" : 86,  "end" : 96 }, 
        {"sofa" : 1,  "begin" : 97,  "end" : 102 }, 
        {"sofa" : 1,  "begin" : 103,  "end" : 109 }, 
        {"sofa" : 1,  "begin" : 110,  "end" : 119 }, 
        {"sofa" : 1,  "begin" : 120,  "end" : 129 }, 
        {"sofa" : 1,  "begin" : 129,  "end" : 130 }, 
        {"sofa" : 1,  "begin" : 131,  "end" : 137 }, 
        {"sofa" : 1,  "begin" : 138,  "end" : 140 }, 
        {"sofa" : 1,  "begin" : 141,  "end" : 147 }, 
        {"sofa" : 1,  "begin" : 148,  "end" : 152 }, 
        {"sofa" : 1,  "begin" : 153,  "end" : 159 }, 
        {"sofa" : 1,  "begin" : 160,  "end" : 162 }, 
        {"sofa" : 1,  "begin" : 163,  "end" : 166 }, 
        {"sofa" : 1,  "begin" : 167,  "end" : 177 }, 
        {"sofa" : 1,  "begin" : 178,  "end" : 186 }, 
        {"sofa" : 1,  "begin" : 187,  "end" : 193 }, 
        {"sofa" : 1,  "begin" : 194,  "end" : 196 }, 
        {"sofa" : 1,  "begin" : 197,  "end" : 200 }, 
        {"sofa" : 1,  "begin" : 201,  "end" : 209 }, 
        {"sofa" : 1,  "begin" : 210,  "end" : 219 }, 
        {"sofa" : 1,  "begin" : 220,  "end" : 222 }, 
        {"sofa" : 1,  "begin" : 223,  "end" : 226 }, 
        {"sofa" : 1,  "begin" : 227,  "end" : 241 }, 
        {"sofa" : 1,  "begin" : 242,  "end" : 248 }, 
        {"sofa" : 1,  "begin" : 249,  "end" : 254 }, 
        {"sofa" : 1,  "begin" : 255,  "end" : 259 }, 
        {"sofa" : 1,  "begin" : 260,  "end" : 265 }, 
        {"sofa" : 1,  "begin" : 266,  "end" : 268 }, 
        {"sofa" : 1,  "begin" : 269,  "end" : 275 }, 
        {"sofa" : 1,  "begin" : 276,  "end" : 281 }, 
        {"sofa" : 1,  "begin" : 281,  "end" : 282 }, 
        {"sofa" : 1,  "begin" : 283,  "end" : 287 }, 
        {"sofa" : 1,  "begin" : 288,  "end" : 293 }, 
        {"sofa" : 1,  "begin" : 294,  "end" : 297 }, 
        {"sofa" : 1,  "begin" : 298,  "end" : 303 }, 
        {"sofa" : 1,  "begin" : 304,  "end" : 308 }, 
        {"sofa" : 1,  "begin" : 309,  "end" : 315 }, 
        {"sofa" : 1,  "begin" : 316,  "end" : 326 }, 
        {"sofa" : 1,  "begin" : 327,  "end" : 330 }, 
        {"sofa" : 1,  "begin" : 331,  "end" : 341 }, 
        {"sofa" : 1,  "begin" : 342,  "end" : 347 }, 
        {"sofa" : 1,  "begin" : 348,  "end" : 350 }, 
        {"sofa" : 1,  "begin" : 351,  "end" : 354 }, 
        {"sofa" : 1,  "begin" : 355,  "end" : 360 }, 
        {"sofa" : 1,  "begin" : 361,  "end" : 364 }, 
        {"sofa" : 1,  "begin" : 365,  "end" : 368 }, 
        {"sofa" : 1,  "begin" : 369,  "end" : 373 }, 
        {"sofa" : 1,  "begin" : 374,  "end" : 380 }, 
        {"sofa" : 1,  "begin" : 381,  "end" : 383 }, 
        {"sofa" : 1,  "begin" : 384,  "end" : 390 }, 
        {"sofa" : 1,  "begin" : 391,  "end" : 398 }, 
        {"sofa" : 1,  "begin" : 399,  "end" : 402 }, 
        {"sofa" : 1,  "begin" : 403,  "end" : 412 }, 
        {"sofa" : 1,  "begin" : 413,  "end" : 417 }, 
        {"sofa" : 1,  "begin" : 418,  "end" : 427 }, 
        {"sofa" : 1,  "begin" : 428,  "end" : 432 }, 
        {"sofa" : 1,  "begin" : 433,  "end" : 445 }, 
        {"sofa" : 1,  "begin" : 446,  "end" : 451 }, 
        {"sofa" : 1,  "begin" : 451,  "end" : 452 }, 
        {"sofa" : 1,  "begin" : 453,  "end" : 458 }, 
        {"sofa" : 1,  "begin" : 459,  "end" : 461 }, 
        {"sofa" : 1,  "begin" : 462,  "end" : 476 }, 
        {"sofa" : 1,  "begin" : 476,  "end" : 477 }, 
        {"sofa" : 1,  "begin" : 478,  "end" : 481 }, 
        {"sofa" : 1,  "begin" : 482,  "end" : 488 }, 
        {"sofa" : 1,  "begin" : 489,  "end" : 491 }, 
        {"sofa" : 1,  "begin" : 492,  "end" : 495 }, 
        {"sofa" : 1,  "begin" : 496,  "end" : 502 }, 
        {"sofa" : 1,  "begin" : 503,  "end" : 507 }, 
        {"sofa" : 1,  "begin" : 508,  "end" : 513 }, 
        {"sofa" : 1,  "begin" : 514,  "end" : 516 }, 
        {"sofa" : 1,  "begin" : 517,  "end" : 523 }, 
        {"sofa" : 1,  "begin" : 524,  "end" : 529 }, 
        {"sofa" : 1,  "begin" : 529,  "end" : 530 }, 
        {"sofa" : 1,  "begin" : 531,  "end" : 534 }, 
        {"sofa" : 1,  "begin" : 535,  "end" : 537 }, 
        {"sofa" : 1,  "begin" : 538,  "end" : 541 }, 
        {"sofa" : 1,  "begin" : 542,  "end" : 543 }, 
        {"sofa" : 1,  "begin" : 544,  "end" : 547 }, 
        {"sofa" : 1,  "begin" : 548,  "end" : 554 }, 
        {"sofa" : 1,  "begin" : 555,  "end" : 561 }, 
        {"sofa" : 1,  "begin" : 562,  "end" : 565 }, 
        {"sofa" : 1,  "begin" : 566,  "end" : 571 }, 
        {"sofa" : 1,  "begin" : 572,  "end" : 575 }, 
        {"sofa" : 1,  "begin" : 576,  "end" : 581 }, 
        {"sofa" : 1,  "begin" : 582,  "end" : 586 }, 
        {"sofa" : 1,  "begin" : 587,  "end" : 593 }, 
        {"sofa" : 1,  "begin" : 594,  "end" : 602 }, 
        {"sofa" : 1,  "begin" : 602,  "end" : 603 }, 
        {"sofa" : 1,  "begin" : 604,  "end" : 608 }, 
        {"sofa" : 1,  "begin" : 609,  "end" : 613 }, 
        {"sofa" : 1,  "begin" : 614,  "end" : 618 }, 
        {"sofa" : 1,  "begin" : 619,  "end" : 627 }, 
        {"sofa" : 1,  "begin" : 628,  "end" : 631 }, 
        {"sofa" : 1,  "begin" : 631,  "end" : 632 }, 
        {"sofa" : 1,  "begin" : 633,  "end" : 636 }, 
        {"sofa" : 1,  "begin" : 637,  "end" : 639 }, 
        {"sofa" : 1,  "begin" : 640,  "end" : 643 }, 
        {"sofa" : 1,  "begin" : 644,  "end" : 650 }, 
        {"sofa" : 1,  "begin" : 651,  "end" : 656 }, 
        {"sofa" : 1,  "begin" : 657,  "end" : 658 }, 
        {"sofa" : 1,  "begin" : 659,  "end" : 663 }, 
        {"sofa" : 1,  "begin" : 664,  "end" : 666 }, 
        {"sofa" : 1,  "begin" : 667,  "end" : 677 }, 
        {"sofa" : 1,  "begin" : 678,  "end" : 686 }, 
        {"sofa" : 1,  "begin" : 687,  "end" : 693 }, 
        {"sofa" : 1,  "begin" : 694,  "end" : 697 }, 
        {"sofa" : 1,  "begin" : 698,  "end" : 706 }, 
        {"sofa" : 1,  "begin" : 707,  "end" : 710 }, 
        {"sofa" : 1,  "begin" : 711,  "end" : 715 }, 
        {"sofa" : 1,  "begin" : 716,  "end" : 725 }, 
        {"sofa" : 1,  "begin" : 725,  "end" : 726 }, 
        {"sofa" : 1,  "begin" : 727,  "end" : 736 }, 
        {"sofa" : 1,  "begin" : 737,  "end" : 738 }, 
        {"sofa" : 1,  "begin" : 739,  "end" : 745 }, 
        {"sofa" : 1,  "begin" : 746,  "end" : 749 }, 
        {"sofa" : 1,  "begin" : 750,  "end" : 758 }, 
        {"sofa" : 1,  "begin" : 759,  "end" : 763 }, 
        {"sofa" : 1,  "begin" : 763,  "end" : 764 }, 
        {"sofa" : 1,  "begin" : 765,  "end" : 767 }, 
        {"sofa" : 1,  "begin" : 768,  "end" : 771 }, 
        {"sofa" : 1,  "begin" : 772,  "end" : 776 }, 
        {"sofa" : 1,  "begin" : 777,  "end" : 779 }, 
        {"sofa" : 1,  "begin" : 780,  "end" : 784 }, 
        {"sofa" : 1,  "begin" : 785,  "end" : 789 }, 
        {"sofa" : 1,  "begin" : 790,  "end" : 793 }, 
        {"sofa" : 1,  "begin" : 794,  "end" : 800 }, 
        {"sofa" : 1,  "begin" : 801,  "end" : 809 }, 
        {"sofa" : 1,  "begin" : 810,  "end" : 812 }, 
        {"sofa" : 1,  "begin" : 813,  "end" : 819 }, 
        {"sofa" : 1,  "begin" : 820,  "end" : 822 }, 
        {"sofa" : 1,  "begin" : 823,  "end" : 830 }, 
        {"sofa" : 1,  "begin" : 831,  "end" : 834 }, 
        {"sofa" : 1,  "begin" : 835,  "end" : 839 }, 
        {"sofa" : 1,  "begin" : 840,  "end" : 844 }, 
        {"sofa" : 1,  "begin" : 845,  "end" : 852 }, 
        {"sofa" : 1,  "begin" : 853,  "end" : 857 }, 
        {"sofa" : 1,  "begin" : 858,  "end" : 860 }, 
        {"sofa" : 1,  "begin" : 861,  "end" : 864 }, 
        {"sofa" : 1,  "begin" : 865,  "end" : 871 }, 
        {"sofa" : 1,  "begin" : 871,  "end" : 872 }, 
        {"sofa" : 1,  "begin" : 873,  "end" : 875 }, 
        {"sofa" : 1,  "begin" : 876,  "end" : 883 }, 
        {"sofa" : 1,  "begin" : 884,  "end" : 889 }, 
        {"sofa" : 1,  "begin" : 889,  "end" : 890 }, 
        {"sofa" : 1,  "begin" : 891,  "end" : 892 }, 
        {"sofa" : 1,  "begin" : 893,  "end" : 898 }, 
        {"sofa" : 1,  "begin" : 899,  "end" : 901 }, 
        {"sofa" : 1,  "begin" : 902,  "end" : 906 }, 
        {"sofa" : 1,  "begin" : 907,  "end" : 914 }, 
        {"sofa" : 1,  "begin" : 915,  "end" : 917 }, 
        {"sofa" : 1,  "begin" : 918,  "end" : 923 }, 
        {"sofa" : 1,  "begin" : 924,  "end" : 926 }, 
        {"sofa" : 1,  "begin" : 927,  "end" : 929 }, 
        {"sofa" : 1,  "begin" : 930,  "end" : 938 }, 
        {"sofa" : 1,  "begin" : 938,  "end" : 939 }, 
        {"sofa" : 1,  "begin" : 940,  "end" : 947 }, 
        {"sofa" : 1,  "begin" : 948,  "end" : 953 }, 
        {"sofa" : 1,  "begin" : 953,  "end" : 954 }, 
        {"sofa" : 1,  "begin" : 955,  "end" : 966 }, 
        {"sofa" : 1,  "begin" : 967,  "end" : 969 }, 
        {"sofa" : 1,  "begin" : 970,  "end" : 973 }, 
        {"sofa" : 1,  "begin" : 974,  "end" : 978 }, 
        {"sofa" : 1,  "begin" : 979,  "end" : 985 }, 
        {"sofa" : 1,  "begin" : 986,  "end" : 991 }, 
        {"sofa" : 1,  "begin" : 992,  "end" : 993 }, 
        {"sofa" : 1,  "begin" : 994,  "end" : 999 }, 
        {"sofa" : 1,  "begin" : 1000,  "end" : 1002 }, 
        {"sofa" : 1,  "begin" : 1003,  "end" : 1013 }, 
        {"sofa" : 1,  "begin" : 1014,  "end" : 1021 }, 
        {"sofa" : 1,  "begin" : 1022,  "end" : 1024 }, 
        {"sofa" : 1,  "begin" : 1025,  "end" : 1026 }, 
        {"sofa" : 1,  "begin" : 1027,  "end" : 1031 }, 
        {"sofa" : 1,  "begin" : 1032,  "end" : 1035 }, 
        {"sofa" : 1,  "begin" : 1036,  "end" : 1045 }, 
        {"sofa" : 1,  "begin" : 1046,  "end" : 1049 }, 
        {"sofa" : 1,  "begin" : 1050,  "end" : 1058 }, 
        {"sofa" : 1,  "begin" : 1059,  "end" : 1066 }, 
        {"sofa" : 1,  "begin" : 1067,  "end" : 1070 }, 
        {"sofa" : 1,  "begin" : 1071,  "end" : 1075 }, 
        {"sofa" : 1,  "begin" : 1076,  "end" : 1085 }, 
        {"sofa" : 1,  "begin" : 1085,  "end" : 1086 }, 
        {"sofa" : 1,  "begin" : 1087,  "end" : 1090 }, 
        {"sofa" : 1,  "begin" : 1091,  "end" : 1093 }, 
        {"sofa" : 1,  "begin" : 1094,  "end" : 1097 }, 
        {"sofa" : 1,  "begin" : 1098,  "end" : 1105 }, 
        {"sofa" : 1,  "begin" : 1106,  "end" : 1111 }, 
        {"sofa" : 1,  "begin" : 1111,  "end" : 1112 }, 
        {"sofa" : 1,  "begin" : 1113,  "end" : 1115 }, 
        {"sofa" : 1,  "begin" : 1116,  "end" : 1124 }, 
        {"sofa" : 1,  "begin" : 1125,  "end" : 1127 }, 
        {"sofa" : 1,  "begin" : 1128,  "end" : 1132 }, 
        {"sofa" : 1,  "begin" : 1133,  "end" : 1140 }, 
        {"sofa" : 1,  "begin" : 1141,  "end" : 1144 }, 
        {"sofa" : 1,  "begin" : 1145,  "end" : 1155 }, 
        {"sofa" : 1,  "begin" : 1155,  "end" : 1156 }, 
        {"sofa" : 1,  "begin" : 1157,  "end" : 1162 }, 
        {"sofa" : 1,  "begin" : 1163,  "end" : 1166 }, 
        {"sofa" : 1,  "begin" : 1167,  "end" : 1173 }, 
        {"sofa" : 1,  "begin" : 1174,  "end" : 1178 }, 
        {"sofa" : 1,  "begin" : 1179,  "end" : 1184 }, 
        {"sofa" : 1,  "begin" : 1185,  "end" : 1187 }, 
        {"sofa" : 1,  "begin" : 1188,  "end" : 1194 }, 
        {"sofa" : 1,  "begin" : 1195,  "end" : 1200 }, 
        {"sofa" : 1,  "begin" : 1200,  "end" : 1201 }, 
        {"sofa" : 1,  "begin" : 1202,  "end" : 1205 }, 
        {"sofa" : 1,  "begin" : 1206,  "end" : 1212 }, 
        {"sofa" : 1,  "begin" : 1213,  "end" : 1223 }, 
        {"sofa" : 1,  "begin" : 1224,  "end" : 1232 }, 
        {"sofa" : 1,  "begin" : 1233,  "end" : 1235 }, 
        {"sofa" : 1,  "begin" : 1236,  "end" : 1242 }, 
        {"sofa" : 1,  "begin" : 1243,  "end" : 1246 }, 
        {"sofa" : 1,  "begin" : 1247,  "end" : 1252 }, 
        {"sofa" : 1,  "begin" : 1253,  "end" : 1257 }, 
        {"sofa" : 1,  "begin" : 1258,  "end" : 1263 }, 
        {"sofa" : 1,  "begin" : 1264,  "end" : 1265 }, 
        {"sofa" : 1,  "begin" : 1266,  "end" : 1271 }, 
        {"sofa" : 1,  "begin" : 1272,  "end" : 1276 }, 
        {"sofa" : 1,  "begin" : 1277,  "end" : 1280 }, 
        {"sofa" : 1,  "begin" : 1281,  "end" : 1289 }, 
        {"sofa" : 1,  "begin" : 1290,  "end" : 1292 }, 
        {"sofa" : 1,  "begin" : 1293,  "end" : 1296 }, 
        {"sofa" : 1,  "begin" : 1297,  "end" : 1305 }, 
        {"sofa" : 1,  "begin" : 1306,  "end" : 1309 }, 
        {"sofa" : 1,  "begin" : 1310,  "end" : 1313 }, 
        {"sofa" : 1,  "begin" : 1314,  "end" : 1324 }, 
        {"sofa" : 1,  "begin" : 1325,  "end" : 1333 }, 
        {"sofa" : 1,  "begin" : 1334,  "end" : 1336 }, 
        {"sofa" : 1,  "begin" : 1337,  "end" : 1339 }, 
        {"sofa" : 1,  "begin" : 1339,  "end" : 1340 }, 
        {"sofa" : 1,  "begin" : 1341,  "end" : 1345 }, 
        {"sofa" : 1,  "begin" : 1346,  "end" : 1353 }, 
        {"sofa" : 1,  "begin" : 1354,  "end" : 1360 }, 
        {"sofa" : 1,  "begin" : 1361,  "end" : 1364 }, 
        {"sofa" : 1,  "begin" : 1365,  "end" : 1373 }, 
        {"sofa" : 1,  "begin" : 1374,  "end" : 1378 }, 
        {"sofa" : 1,  "begin" : 1379,  "end" : 1381 }, 
        {"sofa" : 1,  "begin" : 1382,  "end" : 1385 }, 
        {"sofa" : 1,  "begin" : 1386,  "end" : 1400 }, 
        {"sofa" : 1,  "begin" : 1401,  "end" : 1407 }, 
        {"sofa" : 1,  "begin" : 1408,  "end" : 1413 }, 
        {"sofa" : 1,  "begin" : 1413,  "end" : 1414 }, 
        {"sofa" : 1,  "begin" : 1415,  "end" : 1419 }, 
        {"sofa" : 1,  "begin" : 1420,  "end" : 1432 }, 
        {"sofa" : 1,  "begin" : 1433,  "end" : 1438 }, 
        {"sofa" : 1,  "begin" : 1438,  "end" : 1439 }, 
        {"sofa" : 1,  "begin" : 1440,  "end" : 1443 }, 
        {"sofa" : 1,  "begin" : 1444,  "end" : 1449 }, 
        {"sofa" : 1,  "begin" : 1450,  "end" : 1454 }, 
        {"sofa" : 1,  "begin" : 1455,  "end" : 1461 }, 
        {"sofa" : 1,  "begin" : 1462,  "end" : 1472 }, 
        {"sofa" : 1,  "begin" : 1473,  "end" : 1477 }, 
        {"sofa" : 1,  "begin" : 1478,  "end" : 1488 }, 
        {"sofa" : 1,  "begin" : 1489,  "end" : 1492 }, 
        {"sofa" : 1,  "begin" : 1493,  "end" : 1499 }, 
        {"sofa" : 1,  "begin" : 1500,  "end" : 1502 }, 
        {"sofa" : 1,  "begin" : 1503,  "end" : 1506 }, 
        {"sofa" : 1,  "begin" : 1507,  "end" : 1513 }, 
        {"sofa" : 1,  "begin" : 1514,  "end" : 1516 }, 
        {"sofa" : 1,  "begin" : 1517,  "end" : 1526 }, 
        {"sofa" : 1,  "begin" : 1527,  "end" : 1528 }, 
        {"sofa" : 1,  "begin" : 1528,  "end" : 1530 }, 
        {"sofa" : 1,  "begin" : 1530,  "end" : 1531 }, 
        {"sofa" : 1,  "begin" : 1531,  "end" : 1532 }, 
        {"sofa" : 1,  "begin" : 1533,  "end" : 1539 }, 
        {"sofa" : 1,  "begin" : 1540,  "end" : 1541 }, 
        {"sofa" : 1,  "begin" : 1541,  "end" : 1543 }, 
        {"sofa" : 1,  "begin" : 1543,  "end" : 1544 }, 
        {"sofa" : 1,  "begin" : 1544,  "end" : 1545 }, 
        {"sofa" : 1,  "begin" : 1546,  "end" : 1549 }, 
        {"sofa" : 1,  "begin" : 1550,  "end" : 1554 }, 
        {"sofa" : 1,  "begin" : 1555,  "end" : 1560 }, 
        {"sofa" : 1,  "begin" : 1561,  "end" : 1562 }, 
        {"sofa" : 1,  "begin" : 1562,  "end" : 1564 }, 
        {"sofa" : 1,  "begin" : 1564,  "end" : 1565 }, 
        {"sofa" : 1,  "begin" : 1566,  "end" : 1569 }, 
        {"sofa" : 1,  "begin" : 1570,  "end" : 1574 }, 
        {"sofa" : 1,  "begin" : 1575,  "end" : 1577 }, 
        {"sofa" : 1,  "begin" : 1578,  "end" : 1581 }, 
        {"sofa" : 1,  "begin" : 1582,  "end" : 1588 }, 
        {"sofa" : 1,  "begin" : 1589,  "end" : 1595 }, 
        {"sofa" : 1,  "begin" : 1596,  "end" : 1607 }, 
        {"sofa" : 1,  "begin" : 1608,  "end" : 1611 }, 
        {"sofa" : 1,  "begin" : 1612,  "end" : 1618 }, 
        {"sofa" : 1,  "begin" : 1619,  "end" : 1623 }, 
        {"sofa" : 1,  "begin" : 1624,  "end" : 1626 }, 
        {"sofa" : 1,  "begin" : 1627,  "end" : 1631 }, 
        {"sofa" : 1,  "begin" : 1632,  "end" : 1634 }, 
        {"sofa" : 1,  "begin" : 1635,  "end" : 1641 }, 
        {"sofa" : 1,  "begin" : 1642,  "end" : 1645 }, 
        {"sofa" : 1,  "begin" : 1646,  "end" : 1650 }, 
        {"sofa" : 1,  "begin" : 1651,  "end" : 1659 }, 
        {"sofa" : 1,  "begin" : 1660,  "end" : 1662 }, 
        {"sofa" : 1,  "begin" : 1663,  "end" : 1666 }, 
        {"sofa" : 1,  "begin" : 1667,  "end" : 1674 }, 
        {"sofa" : 1,  "begin" : 1674,  "end" : 1675 }, 
        {"sofa" : 1,  "begin" : 1676,  "end" : 1683 }, 
        {"sofa" : 1,  "begin" : 1683,  "end" : 1684 }, 
        {"sofa" : 1,  "begin" : 1685,  "end" : 1688 }, 
        {"sofa" : 1,  "begin" : 1689,  "end" : 1696 }, 
        {"sofa" : 1,  "begin" : 1697,  "end" : 1700 }, 
        {"sofa" : 1,  "begin" : 1701,  "end" : 1704 }, 
        {"sofa" : 1,  "begin" : 1705,  "end" : 1707 }, 
        {"sofa" : 1,  "begin" : 1708,  "end" : 1710 }, 
        {"sofa" : 1,  "begin" : 1711,  "end" : 1719 }, 
        {"sofa" : 1,  "begin" : 1719,  "end" : 1720 }, 
        {"sofa" : 1,  "begin" : 1721,  "end" : 1729 }, 
        {"sofa" : 1,  "begin" : 1730,  "end" : 1732 }, 
        {"sofa" : 1,  "begin" : 1733,  "end" : 1736 }, 
        {"sofa" : 1,  "begin" : 1736,  "end" : 1737 }, 
        {"sofa" : 1,  "begin" : 1738,  "end" : 1739 }, 
        {"sofa" : 1,  "begin" : 1740,  "end" : 1746 }, 
        {"sofa" : 1,  "begin" : 1747,  "end" : 1753 }, 
        {"sofa" : 1,  "begin" : 1754,  "end" : 1756 }, 
        {"sofa" : 1,  "begin" : 1757,  "end" : 1760 }, 
        {"sofa" : 1,  "begin" : 1761,  "end" : 1775 }, 
        {"sofa" : 1,  "begin" : 1776,  "end" : 1781 }, 
        {"sofa" : 1,  "begin" : 1782,  "end" : 1786 }, 
        {"sofa" : 1,  "begin" : 1787,  "end" : 1791 }, 
        {"sofa" : 1,  "begin" : 1792,  "end" : 1795 }, 
        {"sofa" : 1,  "begin" : 1796,  "end" : 1806 }, 
        {"sofa" : 1,  "begin" : 1807,  "end" : 1809 }, 
        {"sofa" : 1,  "begin" : 1810,  "end" : 1817 }, 
        {"sofa" : 1,  "begin" : 1818,  "end" : 1819 }, 
        {"sofa" : 1,  "begin" : 1820,  "end" : 1825 }, 
        {"sofa" : 1,  "begin" : 1826,  "end" : 1831 }, 
        {"sofa" : 1,  "begin" : 1832,  "end" : 1834 }, 
        {"sofa" : 1,  "begin" : 1835,  "end" : 1838 }, 
        {"sofa" : 1,  "begin" : 1839,  "end" : 1841 }, 
        {"sofa" : 1,  "begin" : 1842,  "end" : 1853 }, 
        {"sofa" : 1,  "begin" : 1854,  "end" : 1856 }, 
        {"sofa" : 1,  "begin" : 1857,  "end" : 1860 }, 
        {"sofa" : 1,  "begin" : 1861,  "end" : 1867 }, 
        {"sofa" : 1,  "begin" : 1868,  "end" : 1871 }, 
        {"sofa" : 1,  "begin" : 1872,  "end" : 1875 }, 
        {"sofa" : 1,  "begin" : 1876,  "end" : 1883 }, 
        {"sofa" : 1,  "begin" : 1883,  "end" : 1884 }, 
        {"sofa" : 1,  "begin" : 1885,  "end" : 1886 }, 
        {"sofa" : 1,  "begin" : 1886,  "end" : 1890 }, 
        {"sofa" : 1,  "begin" : 1891,  "end" : 1896 }, 
        {"sofa" : 1,  "begin" : 1897,  "end" : 1901 }, 
        {"sofa" : 1,  "begin" : 1902,  "end" : 1905 }, 
        {"sofa" : 1,  "begin" : 1906,  "end" : 1914 }, 
        {"sofa" : 1,  "begin" : 1915,  "end" : 1917 }, 
        {"sofa" : 1,  "begin" : 1918,  "end" : 1923 }, 
        {"sofa" : 1,  "begin" : 1924,  "end" : 1930 }, 
        {"sofa" : 1,  "begin" : 1931,  "end" : 1935 }, 
        {"sofa" : 1,  "begin" : 1935,  "end" : 1936 }, 
        {"sofa" : 1,  "begin" : 1937,  "end" : 1941 }, 
        {"sofa" : 1,  "begin" : 1942,  "end" : 1946 }, 
        {"sofa" : 1,  "begin" : 1947,  "end" : 1951 }, 
        {"sofa" : 1,  "begin" : 1951,  "end" : 1952 }, 
        {"sofa" : 1,  "begin" : 1953,  "end" : 1955 }, 
        {"sofa" : 1,  "begin" : 1956,  "end" : 1960 }, 
        {"sofa" : 1,  "begin" : 1961,  "end" : 1967 }, 
        {"sofa" : 1,  "begin" : 1968,  "end" : 1972 }, 
        {"sofa" : 1,  "begin" : 1972,  "end" : 1973 }, 
        {"sofa" : 1,  "begin" : 1973,  "end" : 1974 }, 
        {"sofa" : 1,  "begin" : 1975,  "end" : 1977 }, 
        {"sofa" : 1,  "begin" : 1978,  "end" : 1983 }, 
        {"sofa" : 1,  "begin" : 1983,  "end" : 1984 }, 
        {"sofa" : 1,  "begin" : 1985,  "end" : 1987 }, 
        {"sofa" : 1,  "begin" : 1988,  "end" : 1991 }, 
        {"sofa" : 1,  "begin" : 1992,  "end" : 1995 }, 
        {"sofa" : 1,  "begin" : 1996,  "end" : 2000 }, 
        {"sofa" : 1,  "begin" : 2001,  "end" : 2011 }, 
        {"sofa" : 1,  "begin" : 2012,  "end" : 2017 }, 
        {"sofa" : 1,  "begin" : 2018,  "end" : 2026 }, 
        {"sofa" : 1,  "begin" : 2027,  "end" : 2029 }, 
        {"sofa" : 1,  "begin" : 2030,  "end" : 2031 }, 
        {"sofa" : 1,  "begin" : 2031,  "end" : 2034 }, 
        {"sofa" : 1,  "begin" : 2035,  "end" : 2037 }, 
        {"sofa" : 1,  "begin" : 2038,  "end" : 2041 }, 
        {"sofa" : 1,  "begin" : 2042,  "end" : 2044 }, 
        {"sofa" : 1,  "begin" : 2045,  "end" : 2054 }, 
        {"sofa" : 1,  "begin" : 2055,  "end" : 2065 }, 
        {"sofa" : 1,  "begin" : 2065,  "end" : 2066 }, 
        {"sofa" : 1,  "begin" : 2066,  "end" : 2067 }, 
        {"sofa" : 1,  "begin" : 2068,  "end" : 2070 }, 
        {"sofa" : 1,  "begin" : 2071,  "end" : 2072 }, 
        {"sofa" : 1,  "begin" : 2072,  "end" : 2080 }, 
        {"sofa" : 1,  "begin" : 2081,  "end" : 2088 }, 
        {"sofa" : 1,  "begin" : 2089,  "end" : 2091 }, 
        {"sofa" : 1,  "begin" : 2092,  "end" : 2094 }, 
        {"sofa" : 1,  "begin" : 2095,  "end" : 2105 }, 
        {"sofa" : 1,  "begin" : 2106,  "end" : 2114 }, 
        {"sofa" : 1,  "begin" : 2114,  "end" : 2115 }, 
        {"sofa" : 1,  "begin" : 2116,  "end" : 2119 }, 
        {"sofa" : 1,  "begin" : 2120,  "end" : 2122 }, 
        {"sofa" : 1,  "begin" : 2123,  "end" : 2124 }, 
        {"sofa" : 1,  "begin" : 2124,  "end" : 2133 }, 
        {"sofa" : 1,  "begin" : 2133,  "end" : 2134 }, 
        {"sofa" : 1,  "begin" : 2135,  "end" : 2137 }, 
        {"sofa" : 1,  "begin" : 2138,  "end" : 2141 }, 
        {"sofa" : 1,  "begin" : 2142,  "end" : 2150 }, 
        {"sofa" : 1,  "begin" : 2151,  "end" : 2161 }, 
        {"sofa" : 1,  "begin" : 2162,  "end" : 2165 }, 
        {"sofa" : 1,  "begin" : 2165,  "end" : 2166 }, 
        {"sofa" : 1,  "begin" : 2167,  "end" : 2172 }, 
        {"sofa" : 1,  "begin" : 2173,  "end" : 2176 }, 
        {"sofa" : 1,  "begin" : 2177,  "end" : 2183 }, 
        {"sofa" : 1,  "begin" : 2184,  "end" : 2188 }, 
        {"sofa" : 1,  "begin" : 2188,  "end" : 2189 } ], 
      "Relation" : [
        {"sofa" : 1,  "begin" : 1528,  "end" : 1530,  "Dependent" : 7067,  "Governor" : 6989,  "RelationType" : "Suspect Age" }, 
        {"sofa" : 1,  "begin" : 1541,  "end" : 1543,  "Dependent" : 7223,  "Governor" : 7145,  "RelationType" : "Suspect Age" }, 
        {"sofa" : 1,  "begin" : 1562,  "end" : 1564,  "Dependent" : 7379,  "Governor" : 7301,  "RelationType" : "Suspect Age" } ] } }, 
  "_referenced_fss" : {
    "1" : {"_type" : "Sofa",  "sofaNum" : 1,  "sofaID" : "_InitialView",  "mimeType" : "text",  "sofaString" : "Three TN youngsters shoot videos attacking elephants, booked by forest dept\r\nThree TN youngsters shoot videos attacking elephants, booked by forest dept Videos of the youngsters throwing stones at and slapping elephants in the Udumalaipettai forest range went viral on social media. news Crime The Tamil Nadu forest department has identified three of the young men who were caught on camera teasing and attacking wild elephants near Thirumoorthy hills, close to Udumalaipettai. The videos of the attack went viral on social media, and on May 6 the police booked the three men along with others involved. None have been arrested yet. One of the videos shows a gang of youngsters throwing stones and slapping the wild elephants, including a mother and elephant calf. It can also be seen that the mother elephant is trying to protect its calf from getting hurt in the attack. In another video, a youth is seen running in front of an elephant. Another video, purportedly of the same attack shows a group of youngsters sitting on a tree and recording the violence against the wild elephants. And in yet another video, an elephant is seen chasing the youngsters. After the videos went viral on social media, the forest department officers of Kerala and Tamil Nadu began a probe into the location of the incident and the youngsters involved in it. They finally traced the location back to the Udumalaipettai forest range, near Thirumoorthy hills. The Tamil Nadu Forest department also identified the people in the videos as Kalimuthu (23), Selvam (19), and Arun Kumar (22) who live in the nearby tribal settlements and booked them as well as others who were involved in the attacks. However, the accused are yet to be arrested. Speaking to TNM, a forest ranger in the Udumalaipettai range said that the department is keeping a close watch on all 12 settlements in the region for the accused. “They still have not returned to their houses here. Once they come, we will arrest them,” he added. An FIR has been registered under sections 32 (Ban on use of injurious substances), 39 (Wildlife animals to be government property) and 51 (Penalties) of the Wildlife Protection Act. Watch the videos here: " }, 
    "7067" : {"_type" : "NamedEntity",  "sofa" : 1,  "begin" : 1528,  "end" : 1530,  "value" : "SUS.AGE" }, 
    "6989" : {"_type" : "NamedEntity",  "sofa" : 1,  "begin" : 1517,  "end" : 1526,  "value" : "SUS.NAME" }, 
    "7223" : {"_type" : "NamedEntity",  "sofa" : 1,  "begin" : 1541,  "end" : 1543,  "value" : "SUS.AGE" }, 
    "7145" : {"_type" : "NamedEntity",  "sofa" : 1,  "begin" : 1533,  "end" : 1539,  "value" : "SUS.NAME" }, 
    "7379" : {"_type" : "NamedEntity",  "sofa" : 1,  "begin" : 1562,  "end" : 1564,  "value" : "SUS.AGE" }, 
    "7301" : {"_type" : "NamedEntity",  "sofa" : 1,  "begin" : 1550,  "end" : 1560,  "value" : "SUS.NAME" }, 
    "8323" : {"_type" : "LayerDefinition",  "name" : "de.tudarmstadt.ukp.dkpro.core.api.syntax.type.chunk.Chunk",  "uiName" : "Chunk" }, 
    "8330" : {"_type" : "LayerDefinition",  "name" : "de.tudarmstadt.ukp.dkpro.core.api.syntax.type.dependency.Dependency",  "uiName" : "Dependency" }, 
    "8276" : {"_type" : "LayerDefinition",  "name" : "de.tudarmstadt.ukp.dkpro.core.api.lexmorph.type.pos.POS",  "uiName" : "Part of speech" }, 
    "8352" : {"_type" : "LayerDefinition",  "name" : "webanno.custom.Relation",  "uiName" : "Relation" }, 
    "8269" : {"_type" : "LayerDefinition",  "name" : "de.tudarmstadt.ukp.dkpro.core.api.lexmorph.type.morph.MorphologicalFeatures",  "uiName" : "Morphological features" }, 
    "8258" : {"_type" : "LayerDefinition",  "name" : "de.tudarmstadt.ukp.dkpro.core.api.coref.type.Coreference",  "uiName" : "Coreference" }, 
    "8341" : {"_type" : "LayerDefinition",  "name" : "de.tudarmstadt.ukp.dkpro.core.api.transform.type.SofaChangeAnnotation",  "uiName" : "Orthography Correction" }, 
    "8298" : {"_type" : "LayerDefinition",  "name" : "de.tudarmstadt.ukp.dkpro.core.api.segmentation.type.Lemma",  "uiName" : "Lemma" }, 
    "8287" : {"_type" : "LayerDefinition",  "name" : "de.tudarmstadt.ukp.dkpro.core.api.ner.type.NamedEntity",  "uiName" : "Named entity" }, 
    "8312" : {"_type" : "LayerDefinition",  "name" : "de.tudarmstadt.ukp.dkpro.core.api.semantics.type.SemPred",  "uiName" : "SemPred" }, 
    "8305" : {"_type" : "LayerDefinition",  "name" : "de.tudarmstadt.ukp.dkpro.core.api.segmentation.type.SurfaceForm",  "uiName" : "Surface form" } } }